famli/__init__.py
famli/exec_helpers.py
famli/famli_helpers.py
famli/fastq_helpers.py
famli/run_famli.py
famli-1.2.2.dist-info/licenses/LICENSE.txt
famli-1.2.2.dist-info/METADATA
famli-1.2.2.dist-info/WHEEL
famli-1.2.2.dist-info/entry_points.txt
famli-1.2.2.dist-info/top_level.txt
famli-1.2.2.dist-info/RECORD
