Metadata-Version: 2.4
Name: famli
Version: 1.2.2
Summary: Functional Analysis of Metagenomes by Likelihood Inferrence
Home-page: https://github.com/FredHutch/FAMLI
Author: Samuel Minot
Author-email: sminot@fredhutch.org
Project-URL: Bug Reports, https://github.com/fredhutch/famli/issues
Project-URL: Source, https://github.com/fredhutch/famli/
Keywords: metagenomics microbiome science
Classifier: Intended Audience :: Science/Research
Classifier: License :: OSI Approved :: MIT License
Classifier: Programming Language :: Python :: 2
Classifier: Programming Language :: Python :: 2.7
License-File: LICENSE.txt
Requires-Dist: pandas>=0.20.3
Requires-Dist: biopython>=1.70
Requires-Dist: numpy>=1.13.1
Requires-Dist: scipy>=0.19.1
Requires-Dist: awscli>=1.11.146
Requires-Dist: boto3>=1.4.7
Requires-Dist: python-dateutil>=2.6.0
Dynamic: author
Dynamic: author-email
Dynamic: classifier
Dynamic: description
Dynamic: description-content-type
Dynamic: home-page
Dynamic: keywords
Dynamic: license-file
Dynamic: project-url
Dynamic: requires-dist
Dynamic: summary
